captcha_ocr_devkit/__init__.py
captcha_ocr_devkit/api/__init__.py
captcha_ocr_devkit/api/demo_index.html
captcha_ocr_devkit/api/schemas.py
captcha_ocr_devkit/api/server.py
captcha_ocr_devkit/cli/__init__.py
captcha_ocr_devkit/cli/main.py
captcha_ocr_devkit/core/__init__.py
captcha_ocr_devkit/core/evaluator.py
captcha_ocr_devkit/core/generator.py
captcha_ocr_devkit/core/model.py
captcha_ocr_devkit/core/pipeline.py
captcha_ocr_devkit/core/trainer.py
captcha_ocr_devkit/core/utils.py
captcha_ocr_devkit/core/handlers/__init__.py
captcha_ocr_devkit/core/handlers/base.py
captcha_ocr_devkit/core/handlers/registry.py
captcha_ocr_devkit/examples/__init__.py
captcha_ocr_devkit/examples/handlers/__init__.py
captcha_ocr_devkit/examples/handlers/cnn_handler-README.md
captcha_ocr_devkit/examples/handlers/cnn_handler-config.json
captcha_ocr_devkit/examples/handlers/cnn_handler-requirements.txt
captcha_ocr_devkit/examples/handlers/cnn_handler.py
captcha_ocr_devkit/examples/handlers/crnn_handler-README.md
captcha_ocr_devkit/examples/handlers/crnn_handler-config.json
captcha_ocr_devkit/examples/handlers/crnn_handler-requirements.txt
captcha_ocr_devkit/examples/handlers/crnn_handler.py
captcha_ocr_devkit/examples/handlers/demo_handler-README.md
captcha_ocr_devkit/examples/handlers/demo_handler-config.json
captcha_ocr_devkit/examples/handlers/demo_handler.py
captcha_ocr_devkit/examples/handlers/ocr_common.py
captcha_ocr_devkit/examples/handlers/transformer_handler-README.md
captcha_ocr_devkit/examples/handlers/transformer_handler-config.json
captcha_ocr_devkit/examples/handlers/transformer_handler-requirements.txt
captcha_ocr_devkit/examples/handlers/transformer_handler.py
captcha_ocr_devkit/examples/handlers/transformer_turbo_handler-README.md
captcha_ocr_devkit/examples/handlers/transformer_turbo_handler-config.json
captcha_ocr_devkit/examples/handlers/transformer_turbo_handler-requirements.txt
captcha_ocr_devkit/examples/handlers/transformer_turbo_handler.py
captcha_ocr_devkit-1.20250921.926.dist-info/METADATA
captcha_ocr_devkit-1.20250921.926.dist-info/WHEEL
captcha_ocr_devkit-1.20250921.926.dist-info/entry_points.txt
captcha_ocr_devkit-1.20250921.926.dist-info/top_level.txt
captcha_ocr_devkit-1.20250921.926.dist-info/RECORD
