Metadata-Version: 2.4
Name: captcha-ocr-devkit
Version: 1.20250921.926
Summary: 插件化 CAPTCHA OCR 開發套件 - 輕量級、可擴展、自定義 handlers
Home-page: https://github.com/changyy/py-captcha-ocr-devkit
Author: changyy
Author-email: changyy.csie@gmail.com
Project-URL: Bug Reports, https://github.com/changyy/py-captcha-ocr-devkit/issues
Project-URL: Source, https://github.com/changyy/py-captcha-ocr-devkit
Project-URL: Documentation, https://github.com/changyy/py-captcha-ocr-devkit#readme
Keywords: captcha,ocr,plugin-architecture,handlers,extensible,lightweight,computer-vision,fastapi,cli-tool,text-recognition,image-processing
Classifier: Development Status :: 4 - Beta
Classifier: Intended Audience :: Developers
Classifier: License :: OSI Approved :: MIT License
Classifier: Operating System :: OS Independent
Classifier: Programming Language :: Python :: 3
Classifier: Programming Language :: Python :: 3.8
Classifier: Programming Language :: Python :: 3.9
Classifier: Programming Language :: Python :: 3.10
Classifier: Programming Language :: Python :: 3.11
Classifier: Programming Language :: Python :: 3.12
Classifier: Topic :: Scientific/Engineering :: Artificial Intelligence
Classifier: Topic :: Software Development :: Libraries :: Python Modules
Classifier: Topic :: Multimedia :: Graphics :: Graphics Conversion
Classifier: Topic :: Software Development :: Libraries :: Application Frameworks
Classifier: Framework :: FastAPI
Requires-Python: >=3.8
Provides-Extra: pillow
Requires-Dist: Pillow>=9.0.0; extra == "pillow"
Provides-Extra: opencv
Requires-Dist: opencv-python>=4.6.0; extra == "opencv"
Requires-Dist: numpy>=1.21.0; extra == "opencv"
Provides-Extra: pytorch
Requires-Dist: torch>=2.0.0; extra == "pytorch"
Requires-Dist: torchvision>=0.15.0; extra == "pytorch"
Requires-Dist: numpy>=1.21.0; extra == "pytorch"
Provides-Extra: tensorflow
Requires-Dist: tensorflow>=2.10.0; extra == "tensorflow"
Requires-Dist: numpy>=1.21.0; extra == "tensorflow"
Provides-Extra: tesseract
Requires-Dist: pytesseract>=0.3.10; extra == "tesseract"
Requires-Dist: Pillow>=9.0.0; extra == "tesseract"
Provides-Extra: viz
Requires-Dist: matplotlib>=3.5.0; extra == "viz"
Requires-Dist: seaborn>=0.11.0; extra == "viz"
Requires-Dist: numpy>=1.21.0; extra == "viz"
Provides-Extra: dev
Requires-Dist: pytest>=7.0.0; extra == "dev"
Requires-Dist: pytest-cov>=4.0.0; extra == "dev"
Requires-Dist: pytest-asyncio>=0.21.0; extra == "dev"
Requires-Dist: black>=23.0.0; extra == "dev"
Requires-Dist: flake8>=6.0.0; extra == "dev"
Requires-Dist: isort>=5.12.0; extra == "dev"
Requires-Dist: mypy>=1.0.0; extra == "dev"
Requires-Dist: tqdm>=4.64.0; extra == "dev"
Provides-Extra: docs
Requires-Dist: sphinx>=5.0.0; extra == "docs"
Requires-Dist: sphinx-rtd-theme>=1.0.0; extra == "docs"
Provides-Extra: all
Requires-Dist: Pillow>=9.0.0; extra == "all"
Requires-Dist: matplotlib>=3.5.0; extra == "all"
Requires-Dist: numpy>=1.21.0; extra == "all"
Requires-Dist: opencv-python>=4.6.0; extra == "all"
Requires-Dist: pytesseract>=0.3.10; extra == "all"
Requires-Dist: seaborn>=0.11.0; extra == "all"
Requires-Dist: tensorflow>=2.10.0; extra == "all"
Requires-Dist: torch>=2.0.0; extra == "all"
Requires-Dist: torchvision>=0.15.0; extra == "all"
Dynamic: author
Dynamic: author-email
Dynamic: classifier
Dynamic: description
Dynamic: description-content-type
Dynamic: home-page
Dynamic: keywords
Dynamic: project-url
Dynamic: provides-extra
Dynamic: requires-python
Dynamic: summary
